qttp/__init__.py
qttp/back_test.py
qttp/backtest.py
qttp/other_apis.py
qttp/test.py
qttp/trading_apis.py
qttp/trading_candles.py
qttp/trading_candles2.py
qttp/trading_form.py
qttp/trading_forms.py
qttp/tools/__init__.py
qttp/tools/alerts.py
qttp/tools/data_preprocessing.py
qttp/tools/date.py
qttp/tools/date_interval.py
qttp/tools/exception_handlers.py
qttp/tools/filter.py
qttp/tools/hun_dropbox.py
qttp/tools/indicator.py
qttp/tools/log.py
qttp/tools/mybox.py
qttp/tools/time_span.py
qttp-0.5.19.dist-info/METADATA
qttp-0.5.19.dist-info/WHEEL
qttp-0.5.19.dist-info/top_level.txt
qttp-0.5.19.dist-info/RECORD
