Metadata-Version: 2.1
Name: qttp
Version: 0.5.19
Summary: Quant Trading Tools Packages
Home-page: https://github.com/smarthun0106/qttp
Author: Taehun Kim
Author-email: smarthun0106@gmail.com
License: UNKNOWN
Download-URL: https://github.com/smarthun0106/qttp/archive/master.zip
Keywords: pypi deploy
Platform: UNKNOWN
Classifier: Programming Language :: Python :: 3
Classifier: Programming Language :: Python :: 3.2
Classifier: Programming Language :: Python :: 3.3
Classifier: Programming Language :: Python :: 3.4
Classifier: Programming Language :: Python :: 3.5
Classifier: Programming Language :: Python :: 3.6
Classifier: Programming Language :: Python :: 3.7
Requires-Python: >=3
Requires-Dist: numpy
Requires-Dist: pandas
Requires-Dist: dropbox
